pydantic2es/__init__.py
pydantic2es/main.py
pydantic2es/converters/__init__.py
pydantic2es/converters/dict2mapping.py
pydantic2es/converters/pydantic2dict.py
pydantic2es/helpers/__init__.py
pydantic2es/helpers/helpers.py
pydantic2es/mappings/__init__.py
pydantic2es/mappings/mappings_map.py
pydantic_to_elastic-0.0.4.dist-info/licenses/LICENSE
pydantic_to_elastic-0.0.4.dist-info/METADATA
pydantic_to_elastic-0.0.4.dist-info/WHEEL
pydantic_to_elastic-0.0.4.dist-info/entry_points.txt
pydantic_to_elastic-0.0.4.dist-info/top_level.txt
pydantic_to_elastic-0.0.4.dist-info/RECORD
