Metadata-Version: 2.4
Name: pydantic-to-elastic
Version: 0.0.4
Summary: A simple CLI utility for converting Pydantic models to Elasticsearch mappings
Home-page: https://github.com/malinkinsa/pydantic-to-elastic
Author: Sergey Malinkin
Author-email: malinkinsa@gmail.com
License: MIT
Keywords: pydantic elasticsearch mappings es,elastic
Classifier: Development Status :: 4 - Beta
Classifier: Intended Audience :: Developers
Classifier: License :: OSI Approved :: MIT License
Classifier: Programming Language :: Python
Classifier: Programming Language :: Python :: 3 :: Only
Classifier: Programming Language :: Python :: 3.10
Classifier: Programming Language :: Python :: 3.11
Classifier: Programming Language :: Python :: 3.12
Classifier: Programming Language :: Python :: 3.13
License-File: LICENSE
Requires-Dist: pydantic>=2.0
Dynamic: author
Dynamic: author-email
Dynamic: classifier
Dynamic: description
Dynamic: description-content-type
Dynamic: home-page
Dynamic: keywords
Dynamic: license
Dynamic: license-file
Dynamic: requires-dist
Dynamic: summary
